openmodelica_microgrid_gym/__init__.py
openmodelica_microgrid_gym/agents/__init__.py
openmodelica_microgrid_gym/agents/agent.py
openmodelica_microgrid_gym/agents/episodic.py
openmodelica_microgrid_gym/agents/safeopt.py
openmodelica_microgrid_gym/agents/staticctrl.py
openmodelica_microgrid_gym/agents/util.py
openmodelica_microgrid_gym/aux_ctl/__init__.py
openmodelica_microgrid_gym/aux_ctl/base.py
openmodelica_microgrid_gym/aux_ctl/droop_controllers.py
openmodelica_microgrid_gym/aux_ctl/filter.py
openmodelica_microgrid_gym/aux_ctl/inverter_controllers.py
openmodelica_microgrid_gym/aux_ctl/observers.py
openmodelica_microgrid_gym/aux_ctl/params.py
openmodelica_microgrid_gym/aux_ctl/pi_controllers.py
openmodelica_microgrid_gym/env/__init__.py
openmodelica_microgrid_gym/env/modelica.py
openmodelica_microgrid_gym/env/plot.py
openmodelica_microgrid_gym/env/plotmanager.py
openmodelica_microgrid_gym/env/pyfmi.py
openmodelica_microgrid_gym/execution/__init__.py
openmodelica_microgrid_gym/execution/callbacks.py
openmodelica_microgrid_gym/execution/runner.py
openmodelica_microgrid_gym/net/__init__.py
openmodelica_microgrid_gym/net/base.py
openmodelica_microgrid_gym/net/components.py
openmodelica_microgrid_gym/util/__init__.py
openmodelica_microgrid_gym/util/fastqueue.py
openmodelica_microgrid_gym/util/itertools_.py
openmodelica_microgrid_gym/util/obs_template.py
openmodelica_microgrid_gym/util/randproc.py
openmodelica_microgrid_gym/util/recorder.py
openmodelica_microgrid_gym/util/transforms.py
openmodelica_microgrid_gym-0.4.0.dist-info/AUTHORS.rst
openmodelica_microgrid_gym-0.4.0.dist-info/LICENSE
openmodelica_microgrid_gym-0.4.0.dist-info/METADATA
openmodelica_microgrid_gym-0.4.0.dist-info/WHEEL
openmodelica_microgrid_gym-0.4.0.dist-info/top_level.txt
openmodelica_microgrid_gym-0.4.0.dist-info/RECORD
