Metadata-Version: 2.1
Name: openmodelica-microgrid-gym
Version: 0.4.0
Summary: OpenModelica Microgrid Gym
Home-page: https://github.com/upb-lea/openmodelica-microgrid-gym
Author: LEA - Uni Paderborn
Author-email: upblea@mail.upb.de
License: GNU General Public License v3
Project-URL: Documentation, https://upb-lea.github.io/openmodelica-microgrid-gym/
Project-URL: Source Code, https://github.com/upb-lea/openmodelica-microgrid-gym
Keywords: openmodelica_microgrid_gym
Platform: UNKNOWN
Classifier: Development Status :: 3 - Alpha
Classifier: Intended Audience :: Developers
Classifier: License :: OSI Approved :: GNU General Public License v3 (GPLv3)
Classifier: Natural Language :: English
Classifier: Framework :: Sphinx
Classifier: Topic :: Scientific/Engineering
Classifier: Programming Language :: Python :: 3
Classifier: Programming Language :: Python :: 3.7
Classifier: Programming Language :: Python :: 3.8
Classifier: Operating System :: Microsoft :: Windows
Classifier: Operating System :: POSIX :: Linux
Requires-Python: >=3.7
Requires-Dist: gym (>=0.15.3)
Requires-Dist: numpy (>=1.17.2)
Requires-Dist: matplotlib (>=3.1.1)
Requires-Dist: scipy (>=1.3.1)
Requires-Dist: pandas (>=1.0.1)
Requires-Dist: tqdm (>=4)
Requires-Dist: more-itertools (>=7)
Requires-Dist: numexpr (>=2.7.1)
Requires-Dist: tables (>=3.6.1)
Requires-Dist: stochastic (>=0.6.0)
Requires-Dist: pyyaml (~=5.4)
Requires-Dist: PyFMI (>=2.5)
Requires-Dist: safeopt (>=0.16)
Requires-Dist: GPy (>=1.9.9)
Requires-Dist: future (~=0.18.2)
Requires-Dist: pytest (~=5.4.3)
Requires-Dist: setuptools (~=47.1.1)
Provides-Extra: examples
Requires-Dist: safeopt (>=0.16) ; extra == 'examples'
Requires-Dist: GPy (>=1.9.9) ; extra == 'examples'
